cs3244/__init__.py
cs3244/assignment1.py
cs3244/solution1.py
cs3244_cougar-0.0.12.dist-info/LICENSE
cs3244_cougar-0.0.12.dist-info/METADATA
cs3244_cougar-0.0.12.dist-info/WHEEL
cs3244_cougar-0.0.12.dist-info/top_level.txt
cs3244_cougar-0.0.12.dist-info/RECORD
