Metadata-Version: 2.1
Name: cs3244-cougar
Version: 0.0.12
Summary: NUS CS3244 Assignment
Author: Eugene Lim
Author-email: elimwj@u.nus.edu
License: UNKNOWN
Keywords: cs3244
Platform: UNKNOWN
License-File: LICENSE
Requires-Dist: torch
Requires-Dist: matplotlib
